<?xml version="1.0"?>

<PropertyList>

	<path>../../Models/Wings/a320.leading.3ds</path> 
	<!--texture-path>../Textures/Livery/House</texture-path-->

	<!-- Turn off shadow for performance reason. -->
	<animation>
		<name>Slats.L1.Underside</name>
		<type>noshadow</type>
		<object-name>HIDDEN.L1</object-name>
	</animation>
	
	<animation>
		<name>Slats.L2.Underside</name>
		<type>noshadow</type>
		<object-name>HIDDEN.L2</object-name>
	</animation>
	
	<animation>
		<name>Slats.L3.Underside</name>
		<type>noshadow</type>
		<object-name>HIDDEN.L3</object-name>
	</animation>
	
	<animation>
		<name>Slats.L4.Underside</name>
		<type>noshadow</type>
		<object-name>HIDDEN.L4</object-name>
	</animation>
	
	<animation>
		<name>Slats.L5.Underside</name>
		<type>noshadow</type>
		<object-name>HIDDEN.L5</object-name>
	</animation>
	
	<animation>
		<name>Slats.R1.Underside</name>
		<type>noshadow</type>
		<object-name>HIDDEN.R1</object-name>
	</animation>
	
	<animation>
		<name>Slats.R2.Underside</name>
		<type>noshadow</type>
		<object-name>HIDDEN.R2</object-name>
	</animation>
	
	<animation>
		<name>Slats.R3.Underside</name>
		<type>noshadow</type>
		<object-name>HIDDEN.R3</object-name>
	</animation>
	
	<animation>
		<name>Slats.R4.Underside</name>
		<type>noshadow</type>
		<object-name>HIDDEN.R4</object-name>
	</animation>
	
	<animation>
		<name>Slats.R5.Underside</name>
		<type>noshadow</type>
		<object-name>HIDDEN.R5</object-name>
	</animation>
	
	<!-- Animations for the slats. -->
	<!--animation>
		<name>Slats.L1</name>
		<type>rotate</type>
		<object-name>L1</object-name>
		<object-name>Slats.L1.Underside</object-name>
		<property>/surface-positions/flap-pos-norm</property>
		<factor>20</factor>
		<axis>
			
			<x1-m>2.3152361</x1-m>
			<y1-m>-5.1798925</y1-m>
			<z1-m>-0.5312309</z1-m>
			
			<x2-m>1.0695754</x2-m>
			<y2-m>-2.3605005</y2-m>
			<z2-m>-0.7772275</z2-m>
			
		</axis>
	</animation>
	
	<animation>
		<name>Slats.L2-5</name>
		<type>rotate</type>
		<object-name>L2</object-name>
		<object-name>Slats.L2.Underside</object-name>
		<object-name>L3</object-name>
		<object-name>Slats.L3.Underside</object-name>
		<object-name>L4</object-name>
		<object-name>Slats.L4.Underside</object-name>
		<object-name>L5</object-name>
		<object-name>Slats.L5.Underside</object-name>
		<property>/surface-positions/flap-pos-norm</property>
		<interpolation>
			<entry><ind>0.0</ind><dep>0</dep></entry>
			<entry><ind>0.25</ind><dep>-18</dep></entry>
			<entry><ind>0.375</ind><dep>-18</dep></entry>
			<entry><ind>0.5</ind><dep>-18</dep></entry>
			<entry><ind>1.0</ind><dep>-27</dep></entry>
		</interpolation>
		<axis>
			
			<x1-m>7.8318199</x1-m>
			<y1-m>-161971995</y1-m>
			<z1-m>0.66351</z1-m>
			
			<x2-m>2.6835535</x2-m>
			<y2-m>-5.9247443</y2-m>
			<z2-m>-0.2820382</z2-m>
			
		</axis>
	</animation-->
		
</PropertyList>